mcmodel.cp35-win_amd64.pyd
mcmodel_util/__init__.py
mcmodel_util/util.py
mcmodel-3.0.dist-info/LICENSE
mcmodel-3.0.dist-info/METADATA
mcmodel-3.0.dist-info/WHEEL
mcmodel-3.0.dist-info/top_level.txt
mcmodel-3.0.dist-info/RECORD
